topside/__init__.py
topside/release_info.py
topside/pdl/__init__.py
topside/pdl/exceptions.py
topside/pdl/file.py
topside/pdl/package.py
topside/pdl/parser.py
topside/pdl/utils.py
topside/plumbing/__init__.py
topside/plumbing/exceptions.py
topside/plumbing/invalid_reasons.py
topside/plumbing/plumbing_component.py
topside/plumbing/plumbing_engine.py
topside/plumbing/plumbing_utils.py
topside/plumbing/tests/__init__.py
topside/plumbing/tests/demo_solve.py
topside/plumbing/tests/test_plumbing_component.py
topside/plumbing/tests/test_plumbing_engine_creation.py
topside/plumbing/tests/test_plumbing_engine_editing.py
topside/plumbing/tests/test_plumbing_engine_querying.py
topside/plumbing/tests/test_plumbing_utils.py
topside/plumbing/tests/test_solving_algorithm.py
topside/plumbing/tests/testing_utils.py
topside/procedures/__init__.py
topside/procedures/conditions.py
topside/procedures/procedure.py
topside/procedures/procedures_engine.py
topside/procedures/proclang.py
topside/visualization/__init__.py
topside/visualization/layout.py
topside/visualization/plotting.py
topside/visualization/optimization/__init__.py
topside/visualization/optimization/constraints.py
topside/visualization/optimization/cost_terms.py
topside/visualization/optimization/optimization.py
topside-0.3.0.dist-info/LICENSE
topside-0.3.0.dist-info/METADATA
topside-0.3.0.dist-info/WHEEL
topside-0.3.0.dist-info/top_level.txt
topside-0.3.0.dist-info/RECORD
